LICENSE
README.rst
requirements.txt
setup.py
rasaeco/__init__.py
rasaeco/et.py
rasaeco/intermediate.py
rasaeco/meta.py
rasaeco/model.py
rasaeco/pyrasaeco_render.py
rasaeco/render.py
rasaeco/template.py
rasaeco.egg-info/PKG-INFO
rasaeco.egg-info/SOURCES.txt
rasaeco.egg-info/dependency_links.txt
rasaeco.egg-info/entry_points.txt
rasaeco.egg-info/requires.txt
rasaeco.egg-info/top_level.txt
tests/pyrasaeco_render/__init__.py
tests/pyrasaeco_render/test_graceful_failures.py
tests/pyrasaeco_render/test_that_it_works.py