Metadata-Version: 2.1
Name: rasaeco
Version: 0.0.13
Summary: Analyze software requirements in AECO industry
Home-page: https://github.com/mristin/rasaeco
Author: Marko Ristin
Author-email: marko@ristin.ch
License: License :: OSI Approved :: MIT License
Keywords: BIM architecture civil engineering construction software requirements
Platform: UNKNOWN
Classifier: Development Status :: 5 - Production/Stable
Classifier: License :: OSI Approved :: MIT License
Classifier: Programming Language :: Python :: 3.8
Provides-Extra: dev
